LICENSE
README.md
setup.cfg
setup.py
rulesheet/__init__.py
rulesheet.egg-info/PKG-INFO
rulesheet.egg-info/SOURCES.txt
rulesheet.egg-info/dependency_links.txt
rulesheet.egg-info/top_level.txt