Metadata-Version: 2.1
Name: rulesheet
Version: 0.0.1
Summary: Convert Business Rules defined in a Google Sheet or CSV to Python
Home-page: https://github.com/officeofperformancemanagement/rulesheet
Download-URL: https://github.com/officeofperformancemanagement/rulesheet/tarball/download
Author: Daniel J. Dufour
Author-email: daniel.j.dufour@gmail.com
Keywords: business,data,python,rules
Classifier: Development Status :: 4 - Beta
Classifier: Programming Language :: Python :: 3
Classifier: License :: CC0 1.0 Universal (CC0 1.0) Public Domain Dedication
Classifier: Operating System :: OS Independent
License-File: LICENSE
